.gitignore
LICENSE
README.md
setup.py
django_webdriver/__init__.py
django_webdriver/base.py
django_webdriver/environment.py
django_webdriver/message.py
django_webdriver/webdriver.py
django_webdriver.egg-info/PKG-INFO
django_webdriver.egg-info/SOURCES.txt
django_webdriver.egg-info/dependency_links.txt
django_webdriver.egg-info/requires.txt
django_webdriver.egg-info/top_level.txt
django_webdriver/management/__init__.py
django_webdriver/management/commands/__init__.py
django_webdriver/management/commands/test.py