Metadata-Version: 1.1
Name: django-webdriver
Version: 0.1.2
Summary: Django app to run selenium webdriver tests.
Home-page: https://github.com/optiflows/django-webdriver
Author: Valentin Monte
Author-email: valentin.monte@optiflows.com
License: Apache License 2.0
Platform: UNKNOWN
Classifier: Environment :: Web Environment
Classifier: Framework :: Django
Classifier: Intended Audience :: Developers
Classifier: License :: OSI Approved :: Apache Software License
Classifier: Operating System :: OS Independent
Classifier: Programming Language :: Python
Classifier: Topic :: Software Development :: Libraries :: Python Modules
Classifier: Topic :: Software Development :: Testing
